graphicsmillensatual/__init__.py
graphicsmillensatual/graf.py
graphicsmillensatual-1.1.8.dist-info/LICENSE
graphicsmillensatual-1.1.8.dist-info/METADATA
graphicsmillensatual-1.1.8.dist-info/WHEEL
graphicsmillensatual-1.1.8.dist-info/top_level.txt
graphicsmillensatual-1.1.8.dist-info/RECORD
